Metadata-Version: 1.1
Name: edeposit.amqp.storage
Version: 1.0.0
Summary: Binary storage for the Edeposit project.
Home-page: https://github.com/edeposit/edeposit.amqp.storage/
Author: Edeposit team
Author-email: edeposit@email.cz
License: MIT
Platform: UNKNOWN
Classifier: Development Status :: 3 - Alpha
Classifier: Intended Audience :: Developers
Classifier: Programming Language :: Python :: 2
Classifier: Programming Language :: Python :: 2.7
Classifier: License :: OSI Approved :: MIT License
